botmailroom/__init__.py
botmailroom/botmailroom_types.py
botmailroom/client.py
botmailroom-0.0.14.dist-info/METADATA
botmailroom-0.0.14.dist-info/WHEEL
botmailroom-0.0.14.dist-info/licenses/LICENSE
botmailroom-0.0.14.dist-info/RECORD
