Metadata-Version: 2.3
Name: botmailroom
Version: 0.0.14
Summary: A python client for the BotMailRoom API
Project-URL: Homepage, https://botmailroom.com
Author: BotMailRoom
Classifier: License :: OSI Approved :: Apache Software License
Classifier: Operating System :: OS Independent
Classifier: Programming Language :: Python :: 3
Requires-Python: >=3.9
Requires-Dist: httpx
Requires-Dist: pydantic
